{
  "/_not-found/page": "app/_not-found/page.js",
  "/optimization/page": "app/optimization/page.js",
  "/admin/simulation-control/page": "app/admin/simulation-control/page.js",
  "/implementation/page": "app/implementation/page.js",
  "/page": "app/page.js",
  "/why/page": "app/why/page.js",
  "/portal/efficiency-logs/page": "app/portal/efficiency-logs/page.js",
  "/portal/settings/page": "app/portal/settings/page.js",
  "/portal/thermal-map/page": "app/portal/thermal-map/page.js",
  "/portal/page": "app/portal/page.js",
  "/portal/dashboard/page": "app/portal/dashboard/page.js",
  "/portal/login/page": "app/portal/login/page.js"
}